wheelz_idp_validations/__init__.py
wheelz_idp_validations/id_sanitizer.py
wheelz_idp_validations/pcv1_sanitizer.py
wheelz_idp_validations/pcv2_sanitizer.py
wheelz_idp_validations/sanitize_exception.py
wheelz_idp_validations/exceptions/__init__.py
wheelz_idp_validations/exceptions/cif_exceptions.py
wheelz_idp_validations/exceptions/date_exceptions.py
wheelz_idp_validations/exceptions/full_name_exceptions.py
wheelz_idp_validations/exceptions/gender_exceptions.py
wheelz_idp_validations/exceptions/id_exceptions.py
wheelz_idp_validations/exceptions/plate_exceptions.py
wheelz_idp_validations/exceptions/vin_exceptions.py
wheelz_idp_validations/sanitizers/__init__.py
wheelz_idp_validations/sanitizers/cif.py
wheelz_idp_validations/sanitizers/date.py
wheelz_idp_validations/sanitizers/full_name.py
wheelz_idp_validations/sanitizers/gender.py
wheelz_idp_validations/sanitizers/id_number.py
wheelz_idp_validations/sanitizers/plate.py
wheelz_idp_validations/sanitizers/vin.py
wheelz_idp_validations-2.2.6.dist-info/METADATA
wheelz_idp_validations-2.2.6.dist-info/WHEEL
wheelz_idp_validations-2.2.6.dist-info/RECORD
